LICENSE
MANIFEST.in
README.md
setup.cfg
setup.py
multitrie/__init__.py
multitrie/api.py
multitrie.egg-info/PKG-INFO
multitrie.egg-info/SOURCES.txt
multitrie.egg-info/dependency_links.txt
multitrie.egg-info/top_level.txt