Metadata-Version: 1.1
Name: multitrie
Version: 0.0.4
Summary: Implementation of the trie data structure
Home-page: http://github.com/Pixelapse/multitrie
Author: Pixelapse
Author-email: hello@pixelapse.com
License: The MIT License (MIT)
